pyrevealed/__init__.py
pyrevealed/_kernels.py
pyrevealed/auditor.py
pyrevealed/encoder.py
pyrevealed/lancaster.py
pyrevealed/py.typed
pyrevealed/algorithms/__init__.py
pyrevealed/algorithms/abstract_choice.py
pyrevealed/algorithms/acyclical_p.py
pyrevealed/algorithms/additive.py
pyrevealed/algorithms/aei.py
pyrevealed/algorithms/attention.py
pyrevealed/algorithms/bronars.py
pyrevealed/algorithms/differentiable.py
pyrevealed/algorithms/gapp.py
pyrevealed/algorithms/garp.py
pyrevealed/algorithms/gross_substitutes.py
pyrevealed/algorithms/harp.py
pyrevealed/algorithms/integrability.py
pyrevealed/algorithms/mpi.py
pyrevealed/algorithms/production.py
pyrevealed/algorithms/quasilinear.py
pyrevealed/algorithms/risk.py
pyrevealed/algorithms/separability.py
pyrevealed/algorithms/spatial.py
pyrevealed/algorithms/stochastic.py
pyrevealed/algorithms/utility.py
pyrevealed/algorithms/vei.py
pyrevealed/algorithms/welfare.py
pyrevealed/core/__init__.py
pyrevealed/core/exceptions.py
pyrevealed/core/mixins.py
pyrevealed/core/result.py
pyrevealed/core/session.py
pyrevealed/core/types.py
pyrevealed/graph/__init__.py
pyrevealed/graph/transitive_closure.py
pyrevealed/graph/violation_graph.py
pyrevealed/viz/__init__.py
pyrevealed/viz/plots.py
pyrevealed-0.4.2.dist-info/METADATA
pyrevealed-0.4.2.dist-info/WHEEL
pyrevealed-0.4.2.dist-info/licenses/LICENSE
pyrevealed-0.4.2.dist-info/RECORD
