Metadata-Version: 2.4
Name: pyrevealed
Version: 0.4.2
Summary: Behavioral Signal Analysis for User Understanding - Detect bots, shared accounts, and UI confusion
Project-URL: Homepage, https://github.com/rawatpranjal/PyRevealed
Project-URL: Documentation, https://pyrevealed.readthedocs.io
Project-URL: Repository, https://github.com/rawatpranjal/PyRevealed
Author: PyRevealed Contributors
License: MIT
License-File: LICENSE
Keywords: anomaly-detection,behavioral-analysis,bot-detection,consistency-check,fraud-detection,machine-learning,revealed-preference,user-analytics
Classifier: Development Status :: 3 - Alpha
Classifier: Intended Audience :: Science/Research
Classifier: License :: OSI Approved :: MIT License
Classifier: Operating System :: OS Independent
Classifier: Programming Language :: Python :: 3
Classifier: Programming Language :: Python :: 3.10
Classifier: Programming Language :: Python :: 3.11
Classifier: Programming Language :: Python :: 3.12
Classifier: Topic :: Scientific/Engineering
Classifier: Typing :: Typed
Requires-Python: >=3.10
Requires-Dist: networkx>=3.0
Requires-Dist: numba>=0.58.0
Requires-Dist: numpy>=1.24.0
Requires-Dist: scipy>=1.10.0
Provides-Extra: all
Requires-Dist: jupyter>=1.0.0; extra == 'all'
Requires-Dist: matplotlib>=3.7.0; extra == 'all'
Requires-Dist: mypy>=1.0; extra == 'all'
Requires-Dist: pandas>=2.0.0; extra == 'all'
Requires-Dist: pydata-sphinx-theme>=0.14; extra == 'all'
Requires-Dist: pytest-cov>=4.0; extra == 'all'
Requires-Dist: pytest>=7.0; extra == 'all'
Requires-Dist: ruff>=0.1.0; extra == 'all'
Requires-Dist: seaborn>=0.12.0; extra == 'all'
Requires-Dist: sphinx-autodoc-typehints>=1.25; extra == 'all'
Requires-Dist: sphinx-copybutton>=0.5; extra == 'all'
Requires-Dist: sphinx>=7.0; extra == 'all'
Provides-Extra: dev
Requires-Dist: mypy>=1.0; extra == 'dev'
Requires-Dist: pytest-cov>=4.0; extra == 'dev'
Requires-Dist: pytest>=7.0; extra == 'dev'
Requires-Dist: ruff>=0.1.0; extra == 'dev'
Provides-Extra: docs
Requires-Dist: pydata-sphinx-theme>=0.14; extra == 'docs'
Requires-Dist: sphinx-autodoc-typehints>=1.25; extra == 'docs'
Requires-Dist: sphinx-copybutton>=0.5; extra == 'docs'
Requires-Dist: sphinx>=7.0; extra == 'docs'
Provides-Extra: notebooks
Requires-Dist: jupyter>=1.0.0; extra == 'notebooks'
Requires-Dist: matplotlib>=3.7.0; extra == 'notebooks'
Requires-Dist: pandas>=2.0.0; extra == 'notebooks'
Requires-Dist: seaborn>=0.12.0; extra == 'notebooks'
Provides-Extra: viz
Requires-Dist: matplotlib>=3.7.0; extra == 'viz'
